pytest_cli_fixtures/__init__.py
pytest_cli_fixtures/hooks.py
pytest_cli_fixtures/plugin.py
pytest_cli_fixtures-1.0.dist-info/LICENSE.md
pytest_cli_fixtures-1.0.dist-info/METADATA
pytest_cli_fixtures-1.0.dist-info/WHEEL
pytest_cli_fixtures-1.0.dist-info/entry_points.txt
pytest_cli_fixtures-1.0.dist-info/top_level.txt
pytest_cli_fixtures-1.0.dist-info/RECORD
