Metadata-Version: 2.1
Name: pytest-cli-fixtures
Version: 1.0
Summary: Automatically register fixtures for custom CLI arguments
Author: Chris Wright
License: MIT License
Project-URL: repository, https://github.com/inkychris/pytest-cli-fixtures
Classifier: Framework :: Pytest
Classifier: Intended Audience :: Developers
Classifier: License :: OSI Approved :: MIT License
Classifier: Topic :: Software Development :: Testing
Classifier: Programming Language :: Python
Classifier: Programming Language :: Python :: 3
Classifier: Programming Language :: Python :: 3.7
Classifier: Programming Language :: Python :: 3.8
Classifier: Programming Language :: Python :: 3.9
Classifier: Programming Language :: Python :: 3.10
Requires-Python: >=3.7
License-File: LICENSE.md
Requires-Dist: pytest (~=7.0)
